himage/__init__.py
himage/types.py
himage/io/__init__.py
himage/io/io.py
himage/plot/__init__.py
himage/plot/plot.py
himage/plot/utils.py
himage/utils/__init__.py
himage/utils/utils.py
testing/__init__.py
testing/test_functional.py
testing/test_io.py
testing/test_plot.py
testing/test_utils.py
himage-1.0.0.dist-info/LICENSE
himage-1.0.0.dist-info/METADATA
himage-1.0.0.dist-info/WHEEL
himage-1.0.0.dist-info/top_level.txt
himage-1.0.0.dist-info/RECORD
