Metadata-Version: 2.1
Name: himage
Version: 1.0.0
Summary: A small library, of high level image processing tools
Home-page: https://github.com/mySpecialUsername/highimage
Author: Gor G.
Requires-Python: >=3.10
License-File: LICENSE
Requires-Dist: numpy
Requires-Dist: opencv-python
Requires-Dist: matplotlib
Requires-Dist: PyQt6
